grammarflow/__init__.py
grammarflow/constrain.py
grammarflow/grammars/__init__.py
grammarflow/grammars/error.py
grammarflow/grammars/gnbf.py
grammarflow/grammars/json.py
grammarflow/grammars/template.py
grammarflow/grammars/toml.py
grammarflow/grammars/xml.py
grammarflow/prompt/__init__.py
grammarflow/prompt/builder.py
grammarflow/prompt/template.py
grammarflow/tools/__init__.py
grammarflow/tools/llm.py
grammarflow/tools/pydantic.py
grammarflow/tools/response.py
GrammarFlow-0.1.1.dist-info/LICENSE.txt
GrammarFlow-0.1.1.dist-info/METADATA
GrammarFlow-0.1.1.dist-info/WHEEL
GrammarFlow-0.1.1.dist-info/top_level.txt
GrammarFlow-0.1.1.dist-info/RECORD
