Metadata-Version: 2.1
Name: GrammarFlow
Version: 0.1.1
Summary: Ensuring parsability of LLM responses in agent chains
Home-page: https://github.com/e-lab/SyntaxShaper
Author: AkshathRaghav
Author-email: araviki@purdue.edu
Classifier: Development Status :: 3 - Alpha
Classifier: Intended Audience :: Developers
Classifier: Programming Language :: Python :: 3
Classifier: License :: OSI Approved :: MIT License
Classifier: Operating System :: OS Independent
Requires-Python: >=3.8
License-File: LICENSE.txt
Requires-Dist: pydantic ==1.9.0
Requires-Dist: tiktoken ==0.6.0
Requires-Dist: openai ==1.14.1
Requires-Dist: stopit ==1.1.2
